build/lib/odahuflow/cli/__init__.py
build/lib/odahuflow/cli/__main__.py
build/lib/odahuflow/cli/main.py
build/lib/odahuflow/cli/version.py
build/lib/odahuflow/cli/parsers/__init__.py
build/lib/odahuflow/cli/parsers/bulk.py
build/lib/odahuflow/cli/parsers/completion.py
build/lib/odahuflow/cli/parsers/config.py
build/lib/odahuflow/cli/parsers/connection.py
build/lib/odahuflow/cli/parsers/deployment.py
build/lib/odahuflow/cli/parsers/gppi.py
build/lib/odahuflow/cli/parsers/model.py
build/lib/odahuflow/cli/parsers/packaging.py
build/lib/odahuflow/cli/parsers/packaging_integration.py
build/lib/odahuflow/cli/parsers/route.py
build/lib/odahuflow/cli/parsers/security.py
build/lib/odahuflow/cli/parsers/template.py
build/lib/odahuflow/cli/parsers/toolchain_integration.py
build/lib/odahuflow/cli/parsers/training.py
build/lib/odahuflow/cli/parsers/local/__init__.py
build/lib/odahuflow/cli/parsers/local/packaging.py
build/lib/odahuflow/cli/parsers/local/training.py
build/lib/odahuflow/cli/utils/click_utils.py
build/lib/odahuflow/cli/utils/client.py
build/lib/odahuflow/cli/utils/error_handler.py
build/lib/odahuflow/cli/utils/logs.py
build/lib/odahuflow/cli/utils/output.py
build/lib/odahuflow/cli/utils/verifiers.py
build/lib/tests/parsers/__init__.py
build/lib/tests/parsers/conftest.py
build/lib/tests/parsers/data.py
build/lib/tests/parsers/test_actions_for_all_entities.py
build/lib/tests/parsers/test_completion.py
build/lib/tests/parsers/test_local.py
build/lib/tests/parsers/test_local_packaging.py
build/lib/tests/parsers/test_ordinary_create_edit_actions.py
build/lib/tests/parsers/test_ordinary_delete_actions.py
build/lib/tests/parsers/test_security.py
build/lib/tests/parsers/test_template.py
build/lib/tests/parsers/test_wait_create_edit_actions.py
build/lib/tests/parsers/test_wait_delete_actions.py
odahuflow/cli/__init__.py
odahuflow/cli/__main__.py
odahuflow/cli/main.py
odahuflow/cli/version.py
odahuflow/cli/parsers/__init__.py
odahuflow/cli/parsers/bulk.py
odahu_flow_cli-1.6.1.dist-info/METADATA
odahu_flow_cli-1.6.1.dist-info/WHEEL
odahu_flow_cli-1.6.1.dist-info/entry_points.txt
odahu_flow_cli-1.6.1.dist-info/top_level.txt
odahu_flow_cli-1.6.1.dist-info/RECORD
