Metadata-Version: 2.1
Name: odahu-flow-cli
Version: 1.6.1
Summary: Odahu-flow CLI
Home-page: https://github.com/odahu/odahu-flow
Author: Vlad Tokarev, Vitalik Solodilov
Author-email: vlad.tokarev.94@gmail.com, mcdkr@yandex.ru
License: Apache v2
Platform: UNKNOWN
Requires-Dist: odahu-flow-sdk (==1.6.1)
Requires-Dist: six (>=1.12.0)
Requires-Dist: texttable (>=1.6.1)
Requires-Dist: colorama (>=0.3.9)
Requires-Dist: termcolor (>=1.1.0)
Requires-Dist: click (>=7.0)
Requires-Dist: jsonpath-rw (>=1.4.0)
Requires-Dist: click-completion (>=0.5.2)
